ngauge/Neuron.py
ngauge/TracingPoint.py
ngauge/__init__.py
ngauge/util.py
nGauge-1.0.0.dist-info/LICENSE
nGauge-1.0.0.dist-info/METADATA
nGauge-1.0.0.dist-info/WHEEL
nGauge-1.0.0.dist-info/top_level.txt
nGauge-1.0.0.dist-info/RECORD
