Metadata-Version: 2.1
Name: nGauge
Version: 1.0.0
Summary: Perform morphology measurement on neuron SWC files
Home-page: https://github.com/Cai-Lab-at-University-of-Michigan/nGauge/
Author: Logan Walker
Author-email: loganaw@umich.edu
License: GPLv3
Platform: UNKNOWN
Classifier: Development Status :: 3 - Alpha
Classifier: Intended Audience :: Science/Research
Classifier: License :: OSI Approved :: GNU General Public License v3 (GPLv3)
Classifier: Programming Language :: Python
Classifier: Programming Language :: Python :: 3
Classifier: Programming Language :: Python :: 3 :: Only
Classifier: Topic :: Scientific/Engineering :: Visualization
Classifier: Topic :: Scientific/Engineering :: Image Processing
Classifier: Topic :: Scientific/Engineering :: Bio-Informatics
Classifier: Topic :: Scientific/Engineering
License-File: LICENSE
Requires-Dist: scipy
Requires-Dist: numpy
Requires-Dist: shapely
